thirdweb_ai/__init__.py
thirdweb_ai/_version.py
thirdweb_ai/adapters/autogen/__init__.py
thirdweb_ai/adapters/autogen/autogen.py
thirdweb_ai/adapters/coinbase_agentkit/__init__.py
thirdweb_ai/adapters/coinbase_agentkit/coinbase_agentkit.py
thirdweb_ai/adapters/goat/__init__.py
thirdweb_ai/adapters/goat/goat.py
thirdweb_ai/adapters/google_adk/__init__.py
thirdweb_ai/adapters/google_adk/google_adk.py
thirdweb_ai/adapters/langchain/__init__.py
thirdweb_ai/adapters/langchain/langchain.py
thirdweb_ai/adapters/llama_index/__init__.py
thirdweb_ai/adapters/llama_index/llama_index.py
thirdweb_ai/adapters/mcp/__init__.py
thirdweb_ai/adapters/mcp/mcp.py
thirdweb_ai/adapters/openai/__init__.py
thirdweb_ai/adapters/openai/agents.py
thirdweb_ai/adapters/pydantic_ai/__init__.py
thirdweb_ai/adapters/pydantic_ai/pydantic_ai.py
thirdweb_ai/adapters/smolagents/__init__.py
thirdweb_ai/adapters/smolagents/smolagents.py
thirdweb_ai/common/address.py
thirdweb_ai/common/utils.py
thirdweb_ai/services/__init__.py
thirdweb_ai/services/engine.py
thirdweb_ai/services/engine_cloud.py
thirdweb_ai/services/insight.py
thirdweb_ai/services/nebula.py
thirdweb_ai/services/service.py
thirdweb_ai/services/storage.py
thirdweb_ai/tools/__init__.py
thirdweb_ai/tools/tool.py
thirdweb_ai-0.1.24.dist-info/METADATA
thirdweb_ai-0.1.24.dist-info/WHEEL
thirdweb_ai-0.1.24.dist-info/licenses/LICENSE
thirdweb_ai-0.1.24.dist-info/RECORD
