Metadata-Version: 2.4
Name: thirdweb-ai
Version: 0.1.24
Summary: thirdweb AI
Author-email: thirdweb <support@thirdweb.com>
License-Expression: Apache-2.0
License-File: LICENSE
Keywords: agent,ai,crypto,onchain,sdk,thirdweb,web3
Requires-Python: <4.0,>=3.10
Requires-Dist: aiohttp>=3.11.14
Requires-Dist: httpx<0.29,>=0.28.1
Requires-Dist: jsonref<2,>=1.1.0
Requires-Dist: pydantic<3,>=2.10.6
Requires-Dist: thirdweb-mcp==0.1.24
Requires-Dist: web3>=7.9.0
Provides-Extra: agentkit
Requires-Dist: coinbase-agentkit<0.2,>=0.1.0; extra == 'agentkit'
Provides-Extra: all
Requires-Dist: autogen-core>=0.4.0; extra == 'all'
Requires-Dist: coinbase-agentkit<0.2,>=0.1.0; extra == 'all'
Requires-Dist: goat-sdk>=0.1.0; extra == 'all'
Requires-Dist: google-adk>=1.0.0; extra == 'all'
Requires-Dist: langchain-core>=0.3.0; extra == 'all'
Requires-Dist: llama-index-core>=0.12.0; extra == 'all'
Requires-Dist: mcp>=1.3.0; extra == 'all'
Requires-Dist: openai-agents>=0.0.1; extra == 'all'
Requires-Dist: pydantic-ai>=0.0.39; extra == 'all'
Requires-Dist: smolagents>=1.10.0; extra == 'all'
Provides-Extra: autogen
Requires-Dist: autogen-core>=0.4.0; extra == 'autogen'
Provides-Extra: goat
Requires-Dist: goat-sdk>=0.1.0; extra == 'goat'
Provides-Extra: google-adk
Requires-Dist: google-adk>=1.0.0; extra == 'google-adk'
Requires-Dist: litellm>=v1.70.0; extra == 'google-adk'
Provides-Extra: langchain
Requires-Dist: langchain-core>=0.3.0; extra == 'langchain'
Provides-Extra: llama-index
Requires-Dist: llama-index-core>=0.12.0; extra == 'llama-index'
Provides-Extra: mcp
Requires-Dist: mcp>=1.3.0; extra == 'mcp'
Provides-Extra: openai
Requires-Dist: openai-agents>=0.0.1; extra == 'openai'
Provides-Extra: pydantic-ai
Requires-Dist: pydantic-ai>=0.0.39; extra == 'pydantic-ai'
Provides-Extra: smolagents
Requires-Dist: smolagents>=1.10.0; extra == 'smolagents'
